secret_manager_cli/__init__.py
secret_manager_cli/__main__.py
secret_manager_cli/cli.py
secret_manager_cli/credentials.py
secret_manager_cli/helpers.py
secret_manager_cli/menu.py
secret_manager_cli/session.py
secret_manager_cli-0.1.0.dist-info/LICENSE
secret_manager_cli-0.1.0.dist-info/METADATA
secret_manager_cli-0.1.0.dist-info/WHEEL
secret_manager_cli-0.1.0.dist-info/RECORD
