Metadata-Version: 2.1
Name: secret_manager_cli
Version: 0.1.0
Summary: AWS Secret Manager Cli tool for managing AWS secrets easily
Home-page: https://github.com/fegmorte/aws-secret-manager-cli
License: MIT
Author: Frederic Egmorte
Author-email: frederic.egmorte@gmail.com
Requires-Python: >=3.9,<4.0
Classifier: License :: OSI Approved :: MIT License
Classifier: Operating System :: OS Independent
Classifier: Programming Language :: Python :: 3
Classifier: Programming Language :: Python :: 3.9
Classifier: Programming Language :: Python :: 3.10
Classifier: Programming Language :: Python :: 3.11
Classifier: Programming Language :: Python :: 3.12
Requires-Dist: boto3 (>=1.26.13,<2.0.0)
Requires-Dist: deepdiff (>=6.7.1,<7.0.0)
Requires-Dist: echoprompt (>=0.2.0,<0.3.0)
Requires-Dist: pytest (>=6.2.4,<7.0.0)
Requires-Dist: typer[all] (>=0.9.0,<0.10.0)
Project-URL: Repository, https://github.com/fegmorte/aws-secret-manager-cli
